tests/__init__.py
tests/settings.py
wagtail_picture_tag/__init__.py
wagtail_picture_tag/apps.py
wagtail_picture_tag/tests.py
wagtail_picture_tag/migrations/__init__.py
wagtail_picture_tag/templatetags/__init__.py
wagtail_picture_tag/templatetags/picture_tags.py
wagtail_picture_tag-2.0.1.dist-info/LICENSE
wagtail_picture_tag-2.0.1.dist-info/METADATA
wagtail_picture_tag-2.0.1.dist-info/WHEEL
wagtail_picture_tag-2.0.1.dist-info/top_level.txt
wagtail_picture_tag-2.0.1.dist-info/RECORD
