Metadata-Version: 2.1
Name: wagtail-picture-tag
Version: 2.0.1
Summary: A Wagtail app to add a picture tag.
Author-email: Ben Gosney <bengosney@googlemail.com>
License: GNU General Public License v3 or later (GPLv3+)
Project-URL: Homepage, https://github.com/bengosney/wagtail-picture-tag
Classifier: Environment :: Web Environment
Classifier: Intended Audience :: Developers
Classifier: License :: OSI Approved :: GNU General Public License v3 or later (GPLv3+)
Classifier: Operating System :: OS Independent
Classifier: Programming Language :: Python
Classifier: Programming Language :: Python :: 3
Classifier: Programming Language :: Python :: 3 :: Only
Classifier: Programming Language :: Python :: 3.8
Classifier: Programming Language :: Python :: 3.9
Classifier: Programming Language :: Python :: 3.10
Classifier: Programming Language :: Python :: 3.11
Classifier: Framework :: Wagtail
Classifier: Framework :: Wagtail :: 2
Classifier: Topic :: Internet :: WWW/HTTP
Classifier: Topic :: Internet :: WWW/HTTP :: Dynamic Content
Requires-Python: >=3.10
License-File: LICENSE
Requires-Dist: wagtail
